sqlizer/__init__.py
sqlizer/apiurls.py
sqlizer/config.py
sqlizer/conversionstatus.py
sqlizer/databasetype.py
sqlizer/file.py
sqlizer/filetype.py
sqlizer/propertynames.py
tests/__init__.py
tests/test_file_conversion.py
sqlizer_io_client-1.0.2.dist-info/LICENSE
sqlizer_io_client-1.0.2.dist-info/METADATA
sqlizer_io_client-1.0.2.dist-info/WHEEL
sqlizer_io_client-1.0.2.dist-info/top_level.txt
sqlizer_io_client-1.0.2.dist-info/RECORD
