Metadata-Version: 2.1
Name: sqlizer-io-client
Version: 1.0.2
Summary: A python client library for the SQLizer.io data conversion tool
Home-page: https://sqlizer.io/
Author: D4 Software
Author-email: support@sqlizer.io
License: UNKNOWN
Project-URL: Source, https://github.com/sqlizer-io/sqlizer-client-py
Platform: UNKNOWN
Classifier: Programming Language :: Python :: 3
Classifier: License :: OSI Approved :: MIT License
Classifier: Operating System :: OS Independent
Requires-Python: >=3.6
License-File: LICENSE
Requires-Dist: requests
